systemctl/__init__.py
systemctl/constants/DCmd.py
systemctl/constants/DEnviron.py
systemctl/constants/DExitCode.py
systemctl/constants/DMsg.py
systemctl/constants/DResult.py
systemctl/constants/DSystemCtl.py
systemctl/constants/__init__.py
systemctl-1.2.21.dist-info/METADATA
systemctl-1.2.21.dist-info/WHEEL
systemctl-1.2.21.dist-info/licenses/LICENSE
systemctl-1.2.21.dist-info/RECORD
